src/__init__.py
src/database.py
src/exceptions.py
src/main.py
src/path_walk.py
src/utils.py
src/tests/__init__.py
src/tests/test_create_arg_parser_utils.py
src/tests/test_parse_args_utils.py
src/tests/test_path_walk.py
src/tests/test_retrieve_mime_database.py
src/tests/test_save_file_database.py
src/tests/test_search_path_walk.py
PY_4_findex-0.0.1.dist-info/METADATA
PY_4_findex-0.0.1.dist-info/WHEEL
PY_4_findex-0.0.1.dist-info/entry_points.txt
PY_4_findex-0.0.1.dist-info/top_level.txt
PY_4_findex-0.0.1.dist-info/RECORD
