Metadata-Version: 2.1
Name: PY-4-findex
Version: 0.0.1
Summary: A command line utility to index files based on MIME type
Home-page: https://git.corp.adobe.com/supritiv/PY-4-findex
Author: Suhasini, Miloni, Pragya, Supriti, Srinija
Author-email: sgattu@adobe.com, milonip@adobe.com, pragyag@adobe.com, supritiv@adobe.com, csrinija@adobe.com
License: License
Classifier: Programming Language :: Python :: 3
Classifier: License :: OSI Approved :: MIT License
Classifier: Operating System :: OS Independent
Requires-Python: >=3.7
Requires-Dist: libmagic (==1.0)
Requires-Dist: pylint (==3.0.1)
Requires-Dist: pytest (==7.4.2)
Requires-Dist: python-magic (==0.4.27)
Requires-Dist: tqdm (==4.66.1)
